pytbx.py
lantoolkit-0.1.post0.dist-info/LICENCE
lantoolkit-0.1.post0.dist-info/METADATA
lantoolkit-0.1.post0.dist-info/WHEEL
lantoolkit-0.1.post0.dist-info/top_level.txt
lantoolkit-0.1.post0.dist-info/RECORD
