Metadata-Version: 2.1
Name: lantoolkit
Version: 0.1.post0
Summary: A python toolkit:fix
Home-page: 
Author: lan
Author-email: soft-diyuge@outlook.com
Maintainer: 虚位以待
Maintainer-email: none@none.none
License: MuLan PSL License
Classifier: Development Status :: 3 - Alpha
Classifier: Intended Audience :: Developers
Classifier: Topic :: Software Development :: Build Tools
Classifier: License :: OSI Approved :: MIT License
Classifier: Programming Language :: Python :: 3
Requires-Python: >=3.0
License-File: LICENCE
Requires-Dist: cn2an
Requires-Dist: rich
Requires-Dist: ntplib
Requires-Dist: pyinstaller
Requires-Dist: numpy
Requires-Dist: sympy
Requires-Dist: cython
